prosperity2submit/__init__.py
prosperity2submit/__main__.py
prosperity2submit/core.py
prosperity2submit-0.2.8.dist-info/LICENSE
prosperity2submit-0.2.8.dist-info/METADATA
prosperity2submit-0.2.8.dist-info/WHEEL
prosperity2submit-0.2.8.dist-info/entry_points.txt
prosperity2submit-0.2.8.dist-info/top_level.txt
prosperity2submit-0.2.8.dist-info/RECORD
