Metadata-Version: 2.1
Name: prosperity2submit
Version: 0.2.8
Summary: Command-line submitter for IMC Prosperity 2 algorithms
Author-email: Jasper van Merle <jaspervmerle@gmail.com>
License: MIT License
Project-URL: Repository, https://github.com/jmerle/imc-prosperity-2-submitter
Project-URL: Issues, https://github.com/jmerle/imc-prosperity-2-submitter/issues
Project-URL: Changelog, https://github.com/jmerle/imc-prosperity-2-submitter/releases
Keywords: imc,prosperity,submit,submitter
Classifier: Development Status :: 4 - Beta
Classifier: Intended Audience :: Developers
Classifier: Intended Audience :: Financial and Insurance Industry
Classifier: License :: OSI Approved :: MIT License
Classifier: Programming Language :: Python :: 3
Requires-Python: >=3.9
License-File: LICENSE
Requires-Dist: keyring
Requires-Dist: requests
Requires-Dist: requests-toolbelt
